maillift
