Metadata-Version: 1.1
Name: maillift-python
Version: 1.0.1
Summary: Wrapper around MailLift API
Home-page: https://github.com/marcussaad/mailift-python
Author: Marcus Saad
Author-email: mv.nsaad@gmail.com
License: GPL V3
Download-URL: https://github.com/marcussaad/mailift-python/tarball/1.0.1
Keywords: api,maillift,letters,devtools,Development
Platform: UNKNOWN
Classifier: Development Status :: 4 - Beta
Classifier: Intended Audience :: Developers
Classifier: Topic :: Software Development :: Build Tools
Classifier: License :: OSI Approved :: MIT License
Classifier: Programming Language :: Python :: 2.7
